setup.py
govlab_static_tools.egg-info/PKG-INFO
govlab_static_tools.egg-info/SOURCES.txt
govlab_static_tools.egg-info/dependency_links.txt
govlab_static_tools.egg-info/not-zip-safe
govlab_static_tools.egg-info/requires.txt
govlab_static_tools.egg-info/top_level.txt
govlabstatic/__init__.py
govlabstatic/cli.py
govlabstatic/sass.py
govlabstatic/testing.py
govlabstatic/watcher.py
govlabstatic/webserver.py
test/test_example.py