Metadata-Version: 1.0
Name: govlab-static-tools
Version: 0.1
Summary: Tools for GovLab static site generation
Home-page: http://github.com/govlab/govlab-static-tools
Author: Atul Varma
Author-email: varmaa@gmail.com
License: MIT
Platform: UNKNOWN
